{
  "source": "https://www.movacar.com/en-US/offers",
  "scraped_at": "2026-07-17T00:16:08+00:00",
  "pickup_window": {
    "from": "2026-07-17",
    "to": "2027-07-17"
  },
  "offer_count": 51,
  "offers": [
    {
      "id": "252558_6013_3579",
      "offer_id": "252558",
      "route": "Ueberlingen -> Lörrach",
      "offer_type": 9,
      "vehicle": {
        "make": "NISSA",
        "model": "PRIMASTAR MPV 9S DI AUT",
        "description": null,
        "category": "Mystery Auto",
        "type": "Car",
        "class": null,
        "seats": 5,
        "doors": 5,
        "fuel_type": "Petrol",
        "gear_type": "Can be Manual/Automatic",
        "image": "https://storage.googleapis.com/movacar-prod-assets/eumystery.png"
      },
      "brand_image": "https://storage.googleapis.com/movacar-prod-assets/SixtLogo.png",
      "pickup": {
        "station_id": "2776",
        "city": "Ueberlingen",
        "street": "Heiligenbreite 23",
        "postal_code": "88662",
        "latitude": 47.778202,
        "longitude": 9.202129,
        "code": "Sixt44354"
      },
      "dropoff": {
        "station_id": "2607",
        "city": "Lörrach",
        "street": "Gewerbestr. 6",
        "postal_code": "79539",
        "latitude": 47.62366,
        "longitude": 7.669869,
        "code": "Sixt7353"
      },
      "earliest_pickup": "2026-07-15T22:00:00Z",
      "latest_delivery": "2026-07-17T14:00:00Z",
      "latest_pickup": "2026-07-17T12:00:00+00:00",
      "valid_until": "2026-07-17T09:21:09Z",
      "included_period_hours": 24,
      "extra_period_hours": 24,
      "price": {
        "amount": 1.0,
        "currency": "EUR"
      },
      "free_km": 250,
      "cents_per_extra_km": 50,
      "route_distance_km": 183.6,
      "min_drivers_age": 25,
      "has_connections": false,
      "booking_link": "https://www.movacar.com/en-US/checkout/252558?origin=2776&destination=2607",
      "search_link": "https://www.movacar.com/en-US/offers?pickupDateFrom=2026-07-17&pickupDateTo=2027-07-17"
    },
    {
      "id": "252550_2337_1692",
      "offer_id": "252550",
      "route": "Hameln -> Flensburg",
      "offer_type": 9,
      "vehicle": {
        "make": "NISSA",
        "model": "PRIMASTAR MPV 9S DI AUT",
        "description": null,
        "category": "Mystery Auto",
        "type": "Car",
        "class": null,
        "seats": 5,
        "doors": 5,
        "fuel_type": "Petrol",
        "gear_type": "Can be Manual/Automatic",
        "image": "https://storage.googleapis.com/movacar-prod-assets/eumystery.png"
      },
      "brand_image": "https://storage.googleapis.com/movacar-prod-assets/SixtLogo.png",
      "pickup": {
        "station_id": "5605",
        "city": "Hameln",
        "street": "Kluetstr. 78A",
        "postal_code": "31787",
        "latitude": 52.10354,
        "longitude": 9.335837,
        "code": "Sixt48405"
      },
      "dropoff": {
        "station_id": "2740",
        "city": "Flensburg",
        "street": "Zur Bleiche 45",
        "postal_code": "24941",
        "latitude": 54.771291,
        "longitude": 9.426981,
        "code": "Sixt42926"
      },
      "earliest_pickup": "2026-07-16T17:33:11Z",
      "latest_delivery": "2026-07-18T16:00:00Z",
      "latest_pickup": "2026-07-18T12:00:00+00:00",
      "valid_until": "2026-07-18T09:38:06Z",
      "included_period_hours": 24,
      "extra_period_hours": 24,
      "price": {
        "amount": 1.0,
        "currency": "EUR"
      },
      "free_km": 450,
      "cents_per_extra_km": 50,
      "route_distance_km": 359.3,
      "min_drivers_age": 25,
      "has_connections": false,
      "booking_link": "https://www.movacar.com/en-US/checkout/252550?origin=5605&destination=2740",
      "search_link": "https://www.movacar.com/en-US/offers?pickupDateFrom=2026-07-17&pickupDateTo=2027-07-17"
    },
    {
      "id": "250869_8082_202076",
      "offer_id": "250869",
      "route": "Palermo -> Olbia",
      "offer_type": 5,
      "vehicle": {
        "make": "Fiat",
        "model": "Ducato",
        "description": null,
        "category": "Active Poptop",
        "type": "Camper",
        "class": null,
        "seats": 4,
        "doors": 4,
        "fuel_type": "Diesel",
        "gear_type": "Manual",
        "image": "https://storage.googleapis.com/movacar-prod-assets/ZkJGSEFLKBtrW1B-_NOMADPOPTOP_HEROIMAGE.avif"
      },
      "brand_image": "https://storage.googleapis.com/movacar-prod-assets/IndieCampers.svg",
      "pickup": {
        "station_id": "6118",
        "city": "Palermo",
        "street": "Via Gazzara, 13",
        "postal_code": "90049",
        "latitude": 38.142823,
        "longitude": 13.089665,
        "code": "IC100"
      },
      "dropoff": {
        "station_id": "6163",
        "city": "Olbia",
        "street": "Strada Statale 125 Orientale Sarda",
        "postal_code": "07026",
        "latitude": 40.9030631,
        "longitude": 9.5328432,
        "code": "IC99"
      },
      "earliest_pickup": "2026-07-17T04:00:00Z",
      "latest_delivery": "2026-07-29T19:00:00Z",
      "latest_pickup": "2026-07-29T12:00:00+00:00",
      "valid_until": "2026-07-25T19:00:00Z",
      "included_period_hours": 96,
      "extra_period_hours": 96,
      "price": {
        "amount": 1.0,
        "currency": "EUR"
      },
      "free_km": 935,
      "cents_per_extra_km": 50,
      "route_distance_km": 689.9,
      "min_drivers_age": 18,
      "has_connections": true,
      "booking_link": "https://www.movacar.com/en-US/checkout/250869?origin=6118&destination=6163",
      "search_link": "https://www.movacar.com/en-US/offers?pickupDateFrom=2026-07-17&pickupDateTo=2027-07-17"
    },
    {
      "id": "251198_8082_202076",
      "offer_id": "251198",
      "route": "Palermo -> Olbia",
      "offer_type": 5,
      "vehicle": {
        "make": "Fiat",
        "model": "Ducato",
        "description": null,
        "category": "Active Poptop",
        "type": "Camper",
        "class": null,
        "seats": 4,
        "doors": 4,
        "fuel_type": "Diesel",
        "gear_type": "Manual",
        "image": "https://storage.googleapis.com/movacar-prod-assets/ZkJGSEFLKBtrW1B-_NOMADPOPTOP_HEROIMAGE.avif"
      },
      "brand_image": "https://storage.googleapis.com/movacar-prod-assets/IndieCampers.svg",
      "pickup": {
        "station_id": "6118",
        "city": "Palermo",
        "street": "Via Gazzara, 13",
        "postal_code": "90049",
        "latitude": 38.142823,
        "longitude": 13.089665,
        "code": "IC100"
      },
      "dropoff": {
        "station_id": "6163",
        "city": "Olbia",
        "street": "Strada Statale 125 Orientale Sarda",
        "postal_code": "07026",
        "latitude": 40.9030631,
        "longitude": 9.5328432,
        "code": "IC99"
      },
      "earliest_pickup": "2026-07-17T04:00:00Z",
      "latest_delivery": "2026-07-29T19:00:00Z",
      "latest_pickup": "2026-07-29T12:00:00+00:00",
      "valid_until": "2026-07-25T19:00:00Z",
      "included_period_hours": 96,
      "extra_period_hours": 168,
      "price": {
        "amount": 99.0,
        "currency": "EUR"
      },
      "free_km": 935,
      "cents_per_extra_km": 50,
      "route_distance_km": 689.9,
      "min_drivers_age": 18,
      "has_connections": true,
      "booking_link": "https://www.movacar.com/en-US/checkout/251198?origin=6118&destination=6163",
      "search_link": "https://www.movacar.com/en-US/offers?pickupDateFrom=2026-07-17&pickupDateTo=2027-07-17"
    },
    {
      "id": "251200_8082_202076",
      "offer_id": "251200",
      "route": "Palermo -> Olbia",
      "offer_type": 5,
      "vehicle": {
        "make": "Fiat",
        "model": "Ducato",
        "description": null,
        "category": "Comfort Standard",
        "type": "Camper",
        "class": null,
        "seats": 4,
        "doors": 4,
        "fuel_type": "Diesel",
        "gear_type": "Manual",
        "image": "https://storage.googleapis.com/movacar-prod-assets/ZkIknEFLKBtrW0m0_005Atlas_@Sanojajesus_@Indie_Campers_-29.avif"
      },
      "brand_image": "https://storage.googleapis.com/movacar-prod-assets/IndieCampers.svg",
      "pickup": {
        "station_id": "6118",
        "city": "Palermo",
        "street": "Via Gazzara, 13",
        "postal_code": "90049",
        "latitude": 38.142823,
        "longitude": 13.089665,
        "code": "IC100"
      },
      "dropoff": {
        "station_id": "6163",
        "city": "Olbia",
        "street": "Strada Statale 125 Orientale Sarda",
        "postal_code": "07026",
        "latitude": 40.9030631,
        "longitude": 9.5328432,
        "code": "IC99"
      },
      "earliest_pickup": "2026-07-17T04:00:00Z",
      "latest_delivery": "2026-07-24T19:00:00Z",
      "latest_pickup": "2026-07-24T12:00:00+00:00",
      "valid_until": "2026-07-20T19:00:00Z",
      "included_period_hours": 96,
      "extra_period_hours": 168,
      "price": {
        "amount": 99.0,
        "currency": "EUR"
      },
      "free_km": 935,
      "cents_per_extra_km": 50,
      "route_distance_km": 689.9,
      "min_drivers_age": 18,
      "has_connections": true,
      "booking_link": "https://www.movacar.com/en-US/checkout/251200?origin=6118&destination=6163",
      "search_link": "https://www.movacar.com/en-US/offers?pickupDateFrom=2026-07-17&pickupDateTo=2027-07-17"
    },
    {
      "id": "252439_7532_202075",
      "offer_id": "252439",
      "route": "Nantes -> Châteauneuf-les-Martigues",
      "offer_type": 5,
      "vehicle": {
        "make": "Pilote",
        "model": "V630J or similar",
        "description": null,
        "category": "Active Long Select",
        "type": "Camper",
        "class": null,
        "seats": 4,
        "doors": 4,
        "fuel_type": "Diesel",
        "gear_type": "Automatic",
        "image": "https://storage.googleapis.com/movacar-prod-assets/aacWhFxvIZEnjSMz_Active@5x.avif"
      },
      "brand_image": "https://storage.googleapis.com/movacar-prod-assets/IndieCampers.svg",
      "pickup": {
        "station_id": "6097",
        "city": "Nantes",
        "street": "2 L'Usine",
        "postal_code": "44650",
        "latitude": 46.956933,
        "longitude": -1.6210282,
        "code": "IC76"
      },
      "dropoff": {
        "station_id": "6096",
        "city": "Châteauneuf-les-Martigues",
        "street": "1 Avenue de l'Homme  la Fentre",
        "postal_code": "13220",
        "latitude": 43.3779066,
        "longitude": 5.1441734,
        "code": "IC75"
      },
      "earliest_pickup": "2026-07-17T04:00:00Z",
      "latest_delivery": "2026-07-23T19:00:00Z",
      "latest_pickup": "2026-07-23T09:00:00+00:00",
      "valid_until": "2026-07-18T19:00:00Z",
      "included_period_hours": 120,
      "extra_period_hours": 192,
      "price": {
        "amount": 99.0,
        "currency": "EUR"
      },
      "free_km": 1186,
      "cents_per_extra_km": 50,
      "route_distance_km": 949.7,
      "min_drivers_age": 18,
      "has_connections": true,
      "booking_link": "https://www.movacar.com/en-US/checkout/252439?origin=6097&destination=6096",
      "search_link": "https://www.movacar.com/en-US/offers?pickupDateFrom=2026-07-17&pickupDateTo=2027-07-17"
    },
    {
      "id": "252452_202075_7406",
      "offer_id": "252452",
      "route": "Châteauneuf-les-Martigues -> Bordeaux",
      "offer_type": 5,
      "vehicle": {
        "make": "Fiat",
        "model": "Ducato",
        "description": null,
        "category": "Comfort Standard",
        "type": "Camper",
        "class": null,
        "seats": 4,
        "doors": 4,
        "fuel_type": "Diesel",
        "gear_type": "Manual",
        "image": "https://storage.googleapis.com/movacar-prod-assets/ZkIknEFLKBtrW0m0_005Atlas_@Sanojajesus_@Indie_Campers_-29.avif"
      },
      "brand_image": "https://storage.googleapis.com/movacar-prod-assets/IndieCampers.svg",
      "pickup": {
        "station_id": "6096",
        "city": "Châteauneuf-les-Martigues",
        "street": "1 Avenue de l'Homme  la Fentre",
        "postal_code": "13220",
        "latitude": 43.3779066,
        "longitude": 5.1441734,
        "code": "IC75"
      },
      "dropoff": {
        "station_id": "6094",
        "city": "Bordeaux",
        "street": "65 Av. du Mdoc",
        "postal_code": "33320",
        "latitude": 44.8862672,
        "longitude": -0.6386488,
        "code": "IC73"
      },
      "earliest_pickup": "2026-07-17T04:00:00Z",
      "latest_delivery": "2026-07-30T19:00:00Z",
      "latest_pickup": "2026-07-30T12:00:00+00:00",
      "valid_until": "2026-07-27T19:00:00Z",
      "included_period_hours": 72,
      "extra_period_hours": 144,
      "price": {
        "amount": 99.0,
        "currency": "EUR"
      },
      "free_km": 846,
      "cents_per_extra_km": 50,
      "route_distance_km": 627.0,
      "min_drivers_age": 18,
      "has_connections": false,
      "booking_link": "https://www.movacar.com/en-US/checkout/252452?origin=6096&destination=6094",
      "search_link": "https://www.movacar.com/en-US/offers?pickupDateFrom=2026-07-17&pickupDateTo=2027-07-17"
    },
    {
      "id": "252454_202075_7406",
      "offer_id": "252454",
      "route": "Châteauneuf-les-Martigues -> Bordeaux",
      "offer_type": 5,
      "vehicle": {
        "make": "Fiat",
        "model": "Ducato",
        "description": null,
        "category": "Comfort Standard",
        "type": "Camper",
        "class": null,
        "seats": 4,
        "doors": 4,
        "fuel_type": "Diesel",
        "gear_type": "Manual",
        "image": "https://storage.googleapis.com/movacar-prod-assets/ZkIknEFLKBtrW0m0_005Atlas_@Sanojajesus_@Indie_Campers_-29.avif"
      },
      "brand_image": "https://storage.googleapis.com/movacar-prod-assets/IndieCampers.svg",
      "pickup": {
        "station_id": "6096",
        "city": "Châteauneuf-les-Martigues",
        "street": "1 Avenue de l'Homme  la Fentre",
        "postal_code": "13220",
        "latitude": 43.3779066,
        "longitude": 5.1441734,
        "code": "IC75"
      },
      "dropoff": {
        "station_id": "6094",
        "city": "Bordeaux",
        "street": "65 Av. du Mdoc",
        "postal_code": "33320",
        "latitude": 44.8862672,
        "longitude": -0.6386488,
        "code": "IC73"
      },
      "earliest_pickup": "2026-07-17T04:00:00Z",
      "latest_delivery": "2026-07-30T19:00:00Z",
      "latest_pickup": "2026-07-30T12:00:00+00:00",
      "valid_until": "2026-07-27T19:00:00Z",
      "included_period_hours": 72,
      "extra_period_hours": 144,
      "price": {
        "amount": 99.0,
        "currency": "EUR"
      },
      "free_km": 846,
      "cents_per_extra_km": 50,
      "route_distance_km": 627.0,
      "min_drivers_age": 18,
      "has_connections": false,
      "booking_link": "https://www.movacar.com/en-US/checkout/252454?origin=6096&destination=6094",
      "search_link": "https://www.movacar.com/en-US/offers?pickupDateFrom=2026-07-17&pickupDateTo=2027-07-17"
    },
    {
      "id": "252524_7604_8288",
      "offer_id": "252524",
      "route": "Toulouse -> Amstelveen",
      "offer_type": 5,
      "vehicle": {
        "make": "Fiat",
        "model": "Ducato",
        "description": null,
        "category": "Comfort Standard",
        "type": "Camper",
        "class": null,
        "seats": 4,
        "doors": 4,
        "fuel_type": "Diesel",
        "gear_type": "Manual",
        "image": "https://storage.googleapis.com/movacar-prod-assets/ZkIknEFLKBtrW0m0_005Atlas_@Sanojajesus_@Indie_Campers_-29.avif"
      },
      "brand_image": "https://storage.googleapis.com/movacar-prod-assets/IndieCampers.svg",
      "pickup": {
        "station_id": "6101",
        "city": "Toulouse",
        "street": "9 bis chemin de la Gravire, lot 4",
        "postal_code": "31150",
        "latitude": 43.714399,
        "longitude": 1.3889351,
        "code": "IC80"
      },
      "dropoff": {
        "station_id": "6121",
        "city": "Amstelveen",
        "street": "Grevelingstraat 77",
        "postal_code": "2161",
        "latitude": 52.252707,
        "longitude": 4.5663118,
        "code": "IC103"
      },
      "earliest_pickup": "2026-07-17T04:00:00Z",
      "latest_delivery": "2026-07-26T19:00:00Z",
      "latest_pickup": "2026-07-26T07:00:00+00:00",
      "valid_until": "2026-07-23T19:00:00Z",
      "included_period_hours": 72,
      "extra_period_hours": 72,
      "price": {
        "amount": 99.0,
        "currency": "EUR"
      },
      "free_km": 1378,
      "cents_per_extra_km": 50,
      "route_distance_km": 1172.2,
      "min_drivers_age": 18,
      "has_connections": false,
      "booking_link": "https://www.movacar.com/en-US/checkout/252524?origin=6101&destination=6121",
      "search_link": "https://www.movacar.com/en-US/offers?pickupDateFrom=2026-07-17&pickupDateTo=2027-07-17"
    },
    {
      "id": "252526_7604_8288",
      "offer_id": "252526",
      "route": "Toulouse -> Amstelveen",
      "offer_type": 5,
      "vehicle": {
        "make": "Fiat",
        "model": "Ducato",
        "description": null,
        "category": "Active Poptop Select",
        "type": "Camper",
        "class": null,
        "seats": 4,
        "doors": 4,
        "fuel_type": "Diesel",
        "gear_type": "Manual",
        "image": "https://storage.googleapis.com/movacar-prod-assets/ZkJGSEFLKBtrW1B-_NOMADPOPTOP_HEROIMAGE.avif"
      },
      "brand_image": "https://storage.googleapis.com/movacar-prod-assets/IndieCampers.svg",
      "pickup": {
        "station_id": "6101",
        "city": "Toulouse",
        "street": "9 bis chemin de la Gravire, lot 4",
        "postal_code": "31150",
        "latitude": 43.714399,
        "longitude": 1.3889351,
        "code": "IC80"
      },
      "dropoff": {
        "station_id": "6121",
        "city": "Amstelveen",
        "street": "Grevelingstraat 77",
        "postal_code": "2161",
        "latitude": 52.252707,
        "longitude": 4.5663118,
        "code": "IC103"
      },
      "earliest_pickup": "2026-07-17T04:00:00Z",
      "latest_delivery": "2026-07-30T19:00:00Z",
      "latest_pickup": "2026-07-30T07:00:00+00:00",
      "valid_until": "2026-07-27T19:00:00Z",
      "included_period_hours": 72,
      "extra_period_hours": 72,
      "price": {
        "amount": 99.0,
        "currency": "EUR"
      },
      "free_km": 1378,
      "cents_per_extra_km": 50,
      "route_distance_km": 1172.2,
      "min_drivers_age": 18,
      "has_connections": false,
      "booking_link": "https://www.movacar.com/en-US/checkout/252526?origin=6101&destination=6121",
      "search_link": "https://www.movacar.com/en-US/offers?pickupDateFrom=2026-07-17&pickupDateTo=2027-07-17"
    },
    {
      "id": "252527_8243_592",
      "offer_id": "252527",
      "route": "Bergen -> Berlin",
      "offer_type": 5,
      "vehicle": {
        "make": "Fiat",
        "model": "Ducato",
        "description": null,
        "category": "Active Standard Select",
        "type": "Camper",
        "class": null,
        "seats": 4,
        "doors": 4,
        "fuel_type": "Diesel",
        "gear_type": "Manual",
        "image": "https://storage.googleapis.com/movacar-prod-assets/aD_-qLh8WN-LVkic_ImageGrid-5-.avif"
      },
      "brand_image": "https://storage.googleapis.com/movacar-prod-assets/IndieCampers.svg",
      "pickup": {
        "station_id": "6122",
        "city": "Bergen",
        "street": "Storaneset 32",
        "postal_code": "5260",
        "latitude": 60.4351796,
        "longitude": 5.4621229,
        "code": "IC107"
      },
      "dropoff": {
        "station_id": "6085",
        "city": "Berlin",
        "street": "Adlergestell 350-351",
        "postal_code": "12489",
        "latitude": 52.4281113,
        "longitude": 13.5568964,
        "code": "IC82"
      },
      "earliest_pickup": "2026-07-17T04:00:00Z",
      "latest_delivery": "2026-07-30T19:00:00Z",
      "latest_pickup": "2026-07-30T05:00:00+00:00",
      "valid_until": "2026-07-25T19:00:00Z",
      "included_period_hours": 120,
      "extra_period_hours": 120,
      "price": {
        "amount": 99.0,
        "currency": "EUR"
      },
      "free_km": 1601,
      "cents_per_extra_km": 50,
      "route_distance_km": 1378.5,
      "min_drivers_age": 18,
      "has_connections": false,
      "booking_link": "https://www.movacar.com/en-US/checkout/252527?origin=6122&destination=6085",
      "search_link": "https://www.movacar.com/en-US/offers?pickupDateFrom=2026-07-17&pickupDateTo=2027-07-17"
    },
    {
      "id": "252559_8114_20539",
      "offer_id": "252559",
      "route": "Roma -> Berglern",
      "offer_type": 5,
      "vehicle": {
        "make": "Fiat",
        "model": "Ducato",
        "description": null,
        "category": "Comfort Standard",
        "type": "Camper",
        "class": null,
        "seats": 4,
        "doors": 4,
        "fuel_type": "Diesel",
        "gear_type": "Manual",
        "image": "https://storage.googleapis.com/movacar-prod-assets/ZkIknEFLKBtrW0m0_005Atlas_@Sanojajesus_@Indie_Campers_-29.avif"
      },
      "brand_image": "https://storage.googleapis.com/movacar-prod-assets/IndieCampers.svg",
      "pickup": {
        "station_id": "6119",
        "city": "Roma",
        "street": "Via Cristoforo Sabbadino, 147/b",
        "postal_code": "00148",
        "latitude": 41.817718,
        "longitude": 12.313638,
        "code": "IC101"
      },
      "dropoff": {
        "station_id": "6106",
        "city": "Berglern",
        "street": "Zum Burgstall 4",
        "postal_code": "85459",
        "latitude": 48.3697906,
        "longitude": 11.9297161,
        "code": "IC86"
      },
      "earliest_pickup": "2026-07-17T04:00:00Z",
      "latest_delivery": "2026-07-22T19:00:00Z",
      "latest_pickup": "2026-07-22T09:00:00+00:00",
      "valid_until": "2026-07-17T19:00:00Z",
      "included_period_hours": 120,
      "extra_period_hours": 120,
      "price": {
        "amount": 99.0,
        "currency": "EUR"
      },
      "free_km": 1115,
      "cents_per_extra_km": 50,
      "route_distance_km": 963.2,
      "min_drivers_age": 18,
      "has_connections": false,
      "booking_link": "https://www.movacar.com/en-US/checkout/252559?origin=6119&destination=6106",
      "search_link": "https://www.movacar.com/en-US/offers?pickupDateFrom=2026-07-17&pickupDateTo=2027-07-17"
    },
    {
      "id": "252561_8066_7259",
      "offer_id": "252561",
      "route": "Napoli -> Madrid",
      "offer_type": 5,
      "vehicle": {
        "make": "Fiat",
        "model": "Ducato",
        "description": null,
        "category": "Comfort Standard",
        "type": "Camper",
        "class": null,
        "seats": 4,
        "doors": 4,
        "fuel_type": "Diesel",
        "gear_type": "Manual",
        "image": "https://storage.googleapis.com/movacar-prod-assets/ZkIknEFLKBtrW0m0_005Atlas_@Sanojajesus_@Indie_Campers_-29.avif"
      },
      "brand_image": "https://storage.googleapis.com/movacar-prod-assets/IndieCampers.svg",
      "pickup": {
        "station_id": "6117",
        "city": "Napoli",
        "street": "Via Lucania, 1",
        "postal_code": "80017",
        "latitude": 40.9104355,
        "longitude": 14.2277438,
        "code": "IC98"
      },
      "dropoff": {
        "station_id": "6130",
        "city": "Madrid",
        "street": "Calle de los Fontaneros, 8, Nave 11, San Fernando de Henares",
        "postal_code": "28830",
        "latitude": 40.4446704,
        "longitude": -3.5019514,
        "code": "IC116"
      },
      "earliest_pickup": "2026-07-17T04:00:00Z",
      "latest_delivery": "2026-07-29T19:00:00Z",
      "latest_pickup": "2026-07-28T21:00:00+00:00",
      "valid_until": "2026-07-18T19:00:00Z",
      "included_period_hours": 264,
      "extra_period_hours": 336,
      "price": {
        "amount": 99.0,
        "currency": "EUR"
      },
      "free_km": 2360,
      "cents_per_extra_km": 50,
      "route_distance_km": 2133.1,
      "min_drivers_age": 18,
      "has_connections": false,
      "booking_link": "https://www.movacar.com/en-US/checkout/252561?origin=6117&destination=6130",
      "search_link": "https://www.movacar.com/en-US/offers?pickupDateFrom=2026-07-17&pickupDateTo=2027-07-17"
    },
    {
      "id": "252562_7604_6885",
      "offer_id": "252562",
      "route": "Toulouse -> Brüssel",
      "offer_type": 5,
      "vehicle": {
        "make": "Fiat",
        "model": "Ducato",
        "description": null,
        "category": "Comfort Standard",
        "type": "Camper",
        "class": null,
        "seats": 4,
        "doors": 4,
        "fuel_type": "Diesel",
        "gear_type": "Manual",
        "image": "https://storage.googleapis.com/movacar-prod-assets/ZkIknEFLKBtrW0m0_005Atlas_@Sanojajesus_@Indie_Campers_-29.avif"
      },
      "brand_image": "https://storage.googleapis.com/movacar-prod-assets/IndieCampers.svg",
      "pickup": {
        "station_id": "6101",
        "city": "Toulouse",
        "street": "9 bis chemin de la Gravire, lot 4",
        "postal_code": "31150",
        "latitude": 43.714399,
        "longitude": 1.3889351,
        "code": "IC80"
      },
      "dropoff": {
        "station_id": "6090",
        "city": "Brüssel",
        "street": "Waversebaan 24c",
        "postal_code": "1982",
        "latitude": 50.9691843,
        "longitude": 4.493581,
        "code": "IC66"
      },
      "earliest_pickup": "2026-07-17T04:00:00Z",
      "latest_delivery": "2026-07-24T19:00:00Z",
      "latest_pickup": "2026-07-24T09:00:00+00:00",
      "valid_until": "2026-07-19T19:00:00Z",
      "included_period_hours": 120,
      "extra_period_hours": 168,
      "price": {
        "amount": 99.0,
        "currency": "EUR"
      },
      "free_km": 1181,
      "cents_per_extra_km": 50,
      "route_distance_km": 994.3,
      "min_drivers_age": 18,
      "has_connections": false,
      "booking_link": "https://www.movacar.com/en-US/checkout/252562?origin=6101&destination=6090",
      "search_link": "https://www.movacar.com/en-US/offers?pickupDateFrom=2026-07-17&pickupDateTo=2027-07-17"
    },
    {
      "id": "252566_202076_7930",
      "offer_id": "252566",
      "route": "Olbia -> Cagliari",
      "offer_type": 5,
      "vehicle": {
        "make": "Fiat",
        "model": "Ducato",
        "description": null,
        "category": "Active Poptop",
        "type": "Camper",
        "class": null,
        "seats": 4,
        "doors": 4,
        "fuel_type": "Diesel",
        "gear_type": "Manual",
        "image": "https://storage.googleapis.com/movacar-prod-assets/ZkJGSEFLKBtrW1B-_NOMADPOPTOP_HEROIMAGE.avif"
      },
      "brand_image": "https://storage.googleapis.com/movacar-prod-assets/IndieCampers.svg",
      "pickup": {
        "station_id": "6163",
        "city": "Olbia",
        "street": "Strada Statale 125 Orientale Sarda",
        "postal_code": "07026",
        "latitude": 40.9030631,
        "longitude": 9.5328432,
        "code": "IC99"
      },
      "dropoff": {
        "station_id": "6113",
        "city": "Cagliari",
        "street": "Strada dei Canadesi 2",
        "postal_code": "09032",
        "latitude": 39.278007,
        "longitude": 9.057308,
        "code": "IC94"
      },
      "earliest_pickup": "2026-07-17T04:00:00Z",
      "latest_delivery": "2026-08-01T19:00:00Z",
      "latest_pickup": "2026-08-01T16:00:00+00:00",
      "valid_until": "2026-07-29T19:00:00Z",
      "included_period_hours": 72,
      "extra_period_hours": 144,
      "price": {
        "amount": 1.0,
        "currency": "EUR"
      },
      "free_km": 462,
      "cents_per_extra_km": 50,
      "route_distance_km": 256.2,
      "min_drivers_age": 18,
      "has_connections": false,
      "booking_link": "https://www.movacar.com/en-US/checkout/252566?origin=6163&destination=6113",
      "search_link": "https://www.movacar.com/en-US/offers?pickupDateFrom=2026-07-17&pickupDateTo=2027-07-17"
    },
    {
      "id": "252581_7165_8288",
      "offer_id": "252581",
      "route": "Alacant/Alicante -> Amstelveen",
      "offer_type": 5,
      "vehicle": {
        "make": "Fiat",
        "model": "Ducato",
        "description": null,
        "category": "Comfort Standard",
        "type": "Camper",
        "class": null,
        "seats": 4,
        "doors": 4,
        "fuel_type": "Diesel",
        "gear_type": "Manual",
        "image": "https://storage.googleapis.com/movacar-prod-assets/ZkIknEFLKBtrW0m0_005Atlas_@Sanojajesus_@Indie_Campers_-29.avif"
      },
      "brand_image": "https://storage.googleapis.com/movacar-prod-assets/IndieCampers.svg",
      "pickup": {
        "station_id": "6135",
        "city": "Alacant/Alicante",
        "street": "C. Modelistas, 6, Elda",
        "postal_code": "03640",
        "latitude": 38.447022,
        "longitude": -0.807049,
        "code": "IC122"
      },
      "dropoff": {
        "station_id": "6121",
        "city": "Amstelveen",
        "street": "Grevelingstraat 77",
        "postal_code": "2161",
        "latitude": 52.252707,
        "longitude": 4.5663118,
        "code": "IC103"
      },
      "earliest_pickup": "2026-07-17T04:00:00Z",
      "latest_delivery": "2026-07-26T19:00:00Z",
      "latest_pickup": "2026-07-25T22:00:00+00:00",
      "valid_until": "2026-07-17T19:00:00Z",
      "included_period_hours": 216,
      "extra_period_hours": 216,
      "price": {
        "amount": 99.0,
        "currency": "EUR"
      },
      "free_km": 2249,
      "cents_per_extra_km": 50,
      "route_distance_km": 2023.1,
      "min_drivers_age": 18,
      "has_connections": false,
      "booking_link": "https://www.movacar.com/en-US/checkout/252581?origin=6135&destination=6121",
      "search_link": "https://www.movacar.com/en-US/offers?pickupDateFrom=2026-07-17&pickupDateTo=2027-07-17"
    },
    {
      "id": "252584_7532_7719",
      "offer_id": "252584",
      "route": "Nantes -> London",
      "offer_type": 5,
      "vehicle": {
        "make": "Pilote",
        "model": "G690 GJ or similar",
        "description": null,
        "category": "Comfort Space Select",
        "type": "Camper",
        "class": null,
        "seats": 4,
        "doors": 4,
        "fuel_type": "Diesel",
        "gear_type": "Automatic",
        "image": "https://storage.googleapis.com/movacar-prod-assets/aEFP77h8WN-LVoff_ComfortLongHero.avif"
      },
      "brand_image": "https://storage.googleapis.com/movacar-prod-assets/IndieCampers.svg",
      "pickup": {
        "station_id": "6097",
        "city": "Nantes",
        "street": "2 L'Usine",
        "postal_code": "44650",
        "latitude": 46.956933,
        "longitude": -1.6210282,
        "code": "IC76"
      },
      "dropoff": {
        "station_id": "6142",
        "city": "London",
        "street": "Unit 7, Oades Industrial Estate, Crabtree Rd",
        "postal_code": "TW20 8RN",
        "latitude": 51.4153497,
        "longitude": -0.5315773,
        "code": "IC131"
      },
      "earliest_pickup": "2026-07-17T04:00:00Z",
      "latest_delivery": "2026-07-31T19:00:00Z",
      "latest_pickup": "2026-07-31T10:00:00+00:00",
      "valid_until": "2026-07-27T19:00:00Z",
      "included_period_hours": 96,
      "extra_period_hours": 168,
      "price": {
        "amount": 99.0,
        "currency": "EUR"
      },
      "free_km": 968,
      "cents_per_extra_km": 50,
      "route_distance_km": 827.8,
      "min_drivers_age": 18,
      "has_connections": false,
      "booking_link": "https://www.movacar.com/en-US/checkout/252584?origin=6097&destination=6142",
      "search_link": "https://www.movacar.com/en-US/offers?pickupDateFrom=2026-07-17&pickupDateTo=2027-07-17"
    },
    {
      "id": "252554_2742_240",
      "offer_id": "252554",
      "route": "Homburg -> Aschaffenburg",
      "offer_type": 5,
      "vehicle": {
        "make": "Mystery",
        "model": "Auto",
        "description": null,
        "category": "Mystery Auto",
        "type": "Car",
        "class": null,
        "seats": 5,
        "doors": 5,
        "fuel_type": "Petrol",
        "gear_type": "Can be Manual/Automatic",
        "image": "https://storage.googleapis.com/movacar-prod-assets/eumystery.png"
      },
      "brand_image": "https://storage.googleapis.com/movacar-prod-assets/Europcar.png",
      "pickup": {
        "station_id": "1739",
        "city": "Homburg",
        "street": "BERLINER STR. 130",
        "postal_code": "66424",
        "latitude": 49.3406,
        "longitude": 7.3458,
        "code": "ZQWN01"
      },
      "dropoff": {
        "station_id": "1220",
        "city": "Aschaffenburg",
        "street": "HANAUER STR. 78",
        "postal_code": "63739",
        "latitude": 49.9797,
        "longitude": 9.129,
        "code": "ZCBC01"
      },
      "earliest_pickup": "2026-07-20T04:00:00Z",
      "latest_delivery": "2026-07-24T21:00:00Z",
      "latest_pickup": "2026-07-23T21:00:00+00:00",
      "valid_until": "2026-07-23T21:00:00Z",
      "included_period_hours": 24,
      "extra_period_hours": 24,
      "price": {
        "amount": 1.0,
        "currency": "EUR"
      },
      "free_km": 250,
      "cents_per_extra_km": 50,
      "route_distance_km": 200.1,
      "min_drivers_age": 18,
      "has_connections": false,
      "booking_link": "https://www.movacar.com/en-US/checkout/252554?origin=1739&destination=1220",
      "search_link": "https://www.movacar.com/en-US/offers?pickupDateFrom=2026-07-17&pickupDateTo=2027-07-17"
    },
    {
      "id": "252554_2742_1110",
      "offer_id": "252554",
      "route": "Homburg -> Darmstadt",
      "offer_type": 5,
      "vehicle": {
        "make": "Mystery",
        "model": "Auto",
        "description": null,
        "category": "Mystery Auto",
        "type": "Car",
        "class": null,
        "seats": 5,
        "doors": 5,
        "fuel_type": "Petrol",
        "gear_type": "Can be Manual/Automatic",
        "image": "https://storage.googleapis.com/movacar-prod-assets/eumystery.png"
      },
      "brand_image": "https://storage.googleapis.com/movacar-prod-assets/Europcar.png",
      "pickup": {
        "station_id": "1739",
        "city": "Homburg",
        "street": "BERLINER STR. 130",
        "postal_code": "66424",
        "latitude": 49.3406,
        "longitude": 7.3458,
        "code": "ZQWN01"
      },
      "dropoff": {
        "station_id": "1438",
        "city": "Darmstadt",
        "street": "OTTO-ROEHM-STR. 53",
        "postal_code": "64293",
        "latitude": 49.8894,
        "longitude": 8.6448,
        "code": "DASC01"
      },
      "earliest_pickup": "2026-07-20T04:00:00Z",
      "latest_delivery": "2026-07-24T21:00:00Z",
      "latest_pickup": "2026-07-23T21:00:00+00:00",
      "valid_until": "2026-07-23T21:00:00Z",
      "included_period_hours": 24,
      "extra_period_hours": 24,
      "price": {
        "amount": 1.0,
        "currency": "EUR"
      },
      "free_km": 200,
      "cents_per_extra_km": 50,
      "route_distance_km": 144.5,
      "min_drivers_age": 18,
      "has_connections": false,
      "booking_link": "https://www.movacar.com/en-US/checkout/252554?origin=1739&destination=1438",
      "search_link": "https://www.movacar.com/en-US/offers?pickupDateFrom=2026-07-17&pickupDateTo=2027-07-17"
    },
    {
      "id": "252554_2742_1199",
      "offer_id": "252554",
      "route": "Homburg -> Dillenburg",
      "offer_type": 5,
      "vehicle": {
        "make": "Mystery",
        "model": "Auto",
        "description": null,
        "category": "Mystery Auto",
        "type": "Car",
        "class": null,
        "seats": 5,
        "doors": 5,
        "fuel_type": "Petrol",
        "gear_type": "Can be Manual/Automatic",
        "image": "https://storage.googleapis.com/movacar-prod-assets/eumystery.png"
      },
      "brand_image": "https://storage.googleapis.com/movacar-prod-assets/Europcar.png",
      "pickup": {
        "station_id": "1739",
        "city": "Homburg",
        "street": "BERLINER STR. 130",
        "postal_code": "66424",
        "latitude": 49.3406,
        "longitude": 7.3458,
        "code": "ZQWN01"
      },
      "dropoff": {
        "station_id": "5907",
        "city": "Dillenburg",
        "street": "AUF DER LANGAAR 1",
        "postal_code": "35684",
        "latitude": 50.7684,
        "longitude": 8.2924,
        "code": "SGEE02"
      },
      "earliest_pickup": "2026-07-20T04:00:00Z",
      "latest_delivery": "2026-07-24T21:00:00Z",
      "latest_pickup": "2026-07-23T21:00:00+00:00",
      "valid_until": "2026-07-23T21:00:00Z",
      "included_period_hours": 24,
      "extra_period_hours": 24,
      "price": {
        "amount": 1.0,
        "currency": "EUR"
      },
      "free_km": 350,
      "cents_per_extra_km": 50,
      "route_distance_km": 265.2,
      "min_drivers_age": 18,
      "has_connections": false,
      "booking_link": "https://www.movacar.com/en-US/checkout/252554?origin=1739&destination=5907",
      "search_link": "https://www.movacar.com/en-US/offers?pickupDateFrom=2026-07-17&pickupDateTo=2027-07-17"
    },
    {
      "id": "252554_2742_1727",
      "offer_id": "252554",
      "route": "Homburg -> Frankfurt am Main",
      "offer_type": 5,
      "vehicle": {
        "make": "Mystery",
        "model": "Auto",
        "description": null,
        "category": "Mystery Auto",
        "type": "Car",
        "class": null,
        "seats": 5,
        "doors": 5,
        "fuel_type": "Petrol",
        "gear_type": "Can be Manual/Automatic",
        "image": "https://storage.googleapis.com/movacar-prod-assets/eumystery.png"
      },
      "brand_image": "https://storage.googleapis.com/movacar-prod-assets/Europcar.png",
      "pickup": {
        "station_id": "1739",
        "city": "Homburg",
        "street": "BERLINER STR. 130",
        "postal_code": "66424",
        "latitude": 49.3406,
        "longitude": 7.3458,
        "code": "ZQWN01"
      },
      "dropoff": {
        "station_id": "1279",
        "city": "Frankfurt am Main",
        "street": "IM HAUPTBAHNHOF 1",
        "postal_code": "60329",
        "latitude": 50.1073,
        "longitude": 8.6646,
        "code": "FRAL01"
      },
      "earliest_pickup": "2026-07-20T04:00:00Z",
      "latest_delivery": "2026-07-24T21:00:00Z",
      "latest_pickup": "2026-07-23T21:00:00+00:00",
      "valid_until": "2026-07-23T21:00:00Z",
      "included_period_hours": 24,
      "extra_period_hours": 24,
      "price": {
        "amount": 1.0,
        "currency": "EUR"
      },
      "free_km": 250,
      "cents_per_extra_km": 50,
      "route_distance_km": 170.8,
      "min_drivers_age": 18,
      "has_connections": false,
      "booking_link": "https://www.movacar.com/en-US/checkout/252554?origin=1739&destination=1279",
      "search_link": "https://www.movacar.com/en-US/offers?pickupDateFrom=2026-07-17&pickupDateTo=2027-07-17"
    },
    {
      "id": "252554_2742_1728",
      "offer_id": "252554",
      "route": "Homburg -> Frankfurt",
      "offer_type": 5,
      "vehicle": {
        "make": "Mystery",
        "model": "Auto",
        "description": null,
        "category": "Mystery Auto",
        "type": "Car",
        "class": null,
        "seats": 5,
        "doors": 5,
        "fuel_type": "Petrol",
        "gear_type": "Can be Manual/Automatic",
        "image": "https://storage.googleapis.com/movacar-prod-assets/eumystery.png"
      },
      "brand_image": "https://storage.googleapis.com/movacar-prod-assets/Europcar.png",
      "pickup": {
        "station_id": "1739",
        "city": "Homburg",
        "street": "BERLINER STR. 130",
        "postal_code": "66424",
        "latitude": 49.3406,
        "longitude": 7.3458,
        "code": "ZQWN01"
      },
      "dropoff": {
        "station_id": "1281",
        "city": "Frankfurt",
        "street": "AIRPORT CITY MALL, BEREICH A",
        "postal_code": "60549",
        "latitude": 50.0507,
        "longitude": 8.5687,
        "code": "FRAT01"
      },
      "earliest_pickup": "2026-07-20T04:00:00Z",
      "latest_delivery": "2026-07-24T21:00:00Z",
      "latest_pickup": "2026-07-23T21:00:00+00:00",
      "valid_until": "2026-07-23T21:00:00Z",
      "included_period_hours": 24,
      "extra_period_hours": 24,
      "price": {
        "amount": 1.0,
        "currency": "EUR"
      },
      "free_km": 200,
      "cents_per_extra_km": 50,
      "route_distance_km": 143.0,
      "min_drivers_age": 18,
      "has_connections": false,
      "booking_link": "https://www.movacar.com/en-US/checkout/252554?origin=1739&destination=1281",
      "search_link": "https://www.movacar.com/en-US/offers?pickupDateFrom=2026-07-17&pickupDateTo=2027-07-17"
    },
    {
      "id": "252554_2742_1779",
      "offer_id": "252554",
      "route": "Homburg -> Friedberg",
      "offer_type": 5,
      "vehicle": {
        "make": "Mystery",
        "model": "Auto",
        "description": null,
        "category": "Mystery Auto",
        "type": "Car",
        "class": null,
        "seats": 5,
        "doors": 5,
        "fuel_type": "Petrol",
        "gear_type": "Can be Manual/Automatic",
        "image": "https://storage.googleapis.com/movacar-prod-assets/eumystery.png"
      },
      "brand_image": "https://storage.googleapis.com/movacar-prod-assets/Europcar.png",
      "pickup": {
        "station_id": "1739",
        "city": "Homburg",
        "street": "BERLINER STR. 130",
        "postal_code": "66424",
        "latitude": 49.3406,
        "longitude": 7.3458,
        "code": "ZQWN01"
      },
      "dropoff": {
        "station_id": "1280",
        "city": "Friedberg",
        "street": "KAISERSTR. 156",
        "postal_code": "61169",
        "latitude": 50.3308,
        "longitude": 8.751,
        "code": "FRAN05"
      },
      "earliest_pickup": "2026-07-20T04:00:00Z",
      "latest_delivery": "2026-07-24T21:00:00Z",
      "latest_pickup": "2026-07-23T21:00:00+00:00",
      "valid_until": "2026-07-23T21:00:00Z",
      "included_period_hours": 24,
      "extra_period_hours": 24,
      "price": {
        "amount": 1.0,
        "currency": "EUR"
      },
      "free_km": 250,
      "cents_per_extra_km": 50,
      "route_distance_km": 195.1,
      "min_drivers_age": 18,
      "has_connections": false,
      "booking_link": "https://www.movacar.com/en-US/checkout/252554?origin=1739&destination=1280",
      "search_link": "https://www.movacar.com/en-US/offers?pickupDateFrom=2026-07-17&pickupDateTo=2027-07-17"
    },
    {
      "id": "252554_2742_1831",
      "offer_id": "252554",
      "route": "Homburg -> Fulda",
      "offer_type": 5,
      "vehicle": {
        "make": "Mystery",
        "model": "Auto",
        "description": null,
        "category": "Mystery Auto",
        "type": "Car",
        "class": null,
        "seats": 5,
        "doors": 5,
        "fuel_type": "Petrol",
        "gear_type": "Can be Manual/Automatic",
        "image": "https://storage.googleapis.com/movacar-prod-assets/eumystery.png"
      },
      "brand_image": "https://storage.googleapis.com/movacar-prod-assets/Europcar.png",
      "pickup": {
        "station_id": "1739",
        "city": "Homburg",
        "street": "BERLINER STR. 130",
        "postal_code": "66424",
        "latitude": 49.3406,
        "longitude": 7.3458,
        "code": "ZQWN01"
      },
      "dropoff": {
        "station_id": "1634",
        "city": "Fulda",
        "street": "PETERSBERGER STR. 42",
        "postal_code": "36037",
        "latitude": 50.5501,
        "longitude": 9.6877,
        "code": "GJHC01"
      },
      "earliest_pickup": "2026-07-20T04:00:00Z",
      "latest_delivery": "2026-07-24T21:00:00Z",
      "latest_pickup": "2026-07-23T21:00:00+00:00",
      "valid_until": "2026-07-23T21:00:00Z",
      "included_period_hours": 24,
      "extra_period_hours": 24,
      "price": {
        "amount": 1.0,
        "currency": "EUR"
      },
      "free_km": 350,
      "cents_per_extra_km": 50,
      "route_distance_km": 269.9,
      "min_drivers_age": 18,
      "has_connections": false,
      "booking_link": "https://www.movacar.com/en-US/checkout/252554?origin=1739&destination=1634",
      "search_link": "https://www.movacar.com/en-US/offers?pickupDateFrom=2026-07-17&pickupDateTo=2027-07-17"
    },
    {
      "id": "252554_2742_1973",
      "offer_id": "252554",
      "route": "Homburg -> Gießen",
      "offer_type": 5,
      "vehicle": {
        "make": "Mystery",
        "model": "Auto",
        "description": null,
        "category": "Mystery Auto",
        "type": "Car",
        "class": null,
        "seats": 5,
        "doors": 5,
        "fuel_type": "Petrol",
        "gear_type": "Can be Manual/Automatic",
        "image": "https://storage.googleapis.com/movacar-prod-assets/eumystery.png"
      },
      "brand_image": "https://storage.googleapis.com/movacar-prod-assets/Europcar.png",
      "pickup": {
        "station_id": "1739",
        "city": "Homburg",
        "street": "BERLINER STR. 130",
        "postal_code": "66424",
        "latitude": 49.3406,
        "longitude": 7.3458,
        "code": "ZQWN01"
      },
      "dropoff": {
        "station_id": "4478",
        "city": "Gießen",
        "street": "SCHIFFENBERGER WEG  120",
        "postal_code": "35394",
        "latitude": 50.5691,
        "longitude": 8.6974,
        "code": "ZQYC01"
      },
      "earliest_pickup": "2026-07-20T04:00:00Z",
      "latest_delivery": "2026-07-24T21:00:00Z",
      "latest_pickup": "2026-07-23T21:00:00+00:00",
      "valid_until": "2026-07-23T21:00:00Z",
      "included_period_hours": 24,
      "extra_period_hours": 24,
      "price": {
        "amount": 1.0,
        "currency": "EUR"
      },
      "free_km": 300,
      "cents_per_extra_km": 50,
      "route_distance_km": 226.9,
      "min_drivers_age": 18,
      "has_connections": false,
      "booking_link": "https://www.movacar.com/en-US/checkout/252554?origin=1739&destination=4478",
      "search_link": "https://www.movacar.com/en-US/offers?pickupDateFrom=2026-07-17&pickupDateTo=2027-07-17"
    },
    {
      "id": "252554_2742_2347",
      "offer_id": "252554",
      "route": "Homburg -> Hanau",
      "offer_type": 5,
      "vehicle": {
        "make": "Mystery",
        "model": "Auto",
        "description": null,
        "category": "Mystery Auto",
        "type": "Car",
        "class": null,
        "seats": 5,
        "doors": 5,
        "fuel_type": "Petrol",
        "gear_type": "Can be Manual/Automatic",
        "image": "https://storage.googleapis.com/movacar-prod-assets/eumystery.png"
      },
      "brand_image": "https://storage.googleapis.com/movacar-prod-assets/Europcar.png",
      "pickup": {
        "station_id": "1739",
        "city": "Homburg",
        "street": "BERLINER STR. 130",
        "postal_code": "66424",
        "latitude": 49.3406,
        "longitude": 7.3458,
        "code": "ZQWN01"
      },
      "dropoff": {
        "station_id": "1705",
        "city": "Hanau",
        "street": "AUHEIMER STR. 2",
        "postal_code": "63450",
        "latitude": 50.1216,
        "longitude": 8.9256,
        "code": "HNUC03"
      },
      "earliest_pickup": "2026-07-20T04:00:00Z",
      "latest_delivery": "2026-07-24T21:00:00Z",
      "latest_pickup": "2026-07-23T21:00:00+00:00",
      "valid_until": "2026-07-23T21:00:00Z",
      "included_period_hours": 24,
      "extra_period_hours": 24,
      "price": {
        "amount": 1.0,
        "currency": "EUR"
      },
      "free_km": 250,
      "cents_per_extra_km": 50,
      "route_distance_km": 188.8,
      "min_drivers_age": 18,
      "has_connections": false,
      "booking_link": "https://www.movacar.com/en-US/checkout/252554?origin=1739&destination=1705",
      "search_link": "https://www.movacar.com/en-US/offers?pickupDateFrom=2026-07-17&pickupDateTo=2027-07-17"
    },
    {
      "id": "252554_2742_3334",
      "offer_id": "252554",
      "route": "Homburg -> Langen in Hessen",
      "offer_type": 5,
      "vehicle": {
        "make": "Mystery",
        "model": "Auto",
        "description": null,
        "category": "Mystery Auto",
        "type": "Car",
        "class": null,
        "seats": 5,
        "doors": 5,
        "fuel_type": "Petrol",
        "gear_type": "Can be Manual/Automatic",
        "image": "https://storage.googleapis.com/movacar-prod-assets/eumystery.png"
      },
      "brand_image": "https://storage.googleapis.com/movacar-prod-assets/Europcar.png",
      "pickup": {
        "station_id": "1739",
        "city": "Homburg",
        "street": "BERLINER STR. 130",
        "postal_code": "66424",
        "latitude": 49.3406,
        "longitude": 7.3458,
        "code": "ZQWN01"
      },
      "dropoff": {
        "station_id": "1781",
        "city": "Langen in Hessen",
        "street": "AMPERESTR. 7-11",
        "postal_code": "63225",
        "latitude": 49.9982,
        "longitude": 8.652,
        "code": "NWBW02"
      },
      "earliest_pickup": "2026-07-20T04:00:00Z",
      "latest_delivery": "2026-07-24T21:00:00Z",
      "latest_pickup": "2026-07-23T21:00:00+00:00",
      "valid_until": "2026-07-23T21:00:00Z",
      "included_period_hours": 24,
      "extra_period_hours": 24,
      "price": {
        "amount": 1.0,
        "currency": "EUR"
      },
      "free_km": 200,
      "cents_per_extra_km": 50,
      "route_distance_km": 154.9,
      "min_drivers_age": 18,
      "has_connections": false,
      "booking_link": "https://www.movacar.com/en-US/checkout/252554?origin=1739&destination=1781",
      "search_link": "https://www.movacar.com/en-US/offers?pickupDateFrom=2026-07-17&pickupDateTo=2027-07-17"
    },
    {
      "id": "252554_2742_3675",
      "offer_id": "252554",
      "route": "Homburg -> Mainz",
      "offer_type": 5,
      "vehicle": {
        "make": "Mystery",
        "model": "Auto",
        "description": null,
        "category": "Mystery Auto",
        "type": "Car",
        "class": null,
        "seats": 5,
        "doors": 5,
        "fuel_type": "Petrol",
        "gear_type": "Can be Manual/Automatic",
        "image": "https://storage.googleapis.com/movacar-prod-assets/eumystery.png"
      },
      "brand_image": "https://storage.googleapis.com/movacar-prod-assets/Europcar.png",
      "pickup": {
        "station_id": "1739",
        "city": "Homburg",
        "street": "BERLINER STR. 130",
        "postal_code": "66424",
        "latitude": 49.3406,
        "longitude": 7.3458,
        "code": "ZQWN01"
      },
      "dropoff": {
        "station_id": "1226",
        "city": "Mainz",
        "street": "RHEINALLEE 104",
        "postal_code": "55120",
        "latitude": 50.0216,
        "longitude": 8.2413,
        "code": "QMZC01"
      },
      "earliest_pickup": "2026-07-20T04:00:00Z",
      "latest_delivery": "2026-07-24T21:00:00Z",
      "latest_pickup": "2026-07-23T21:00:00+00:00",
      "valid_until": "2026-07-23T21:00:00Z",
      "included_period_hours": 24,
      "extra_period_hours": 24,
      "price": {
        "amount": 1.0,
        "currency": "EUR"
      },
      "free_km": 200,
      "cents_per_extra_km": 50,
      "route_distance_km": 126.0,
      "min_drivers_age": 18,
      "has_connections": false,
      "booking_link": "https://www.movacar.com/en-US/checkout/252554?origin=1739&destination=1226",
      "search_link": "https://www.movacar.com/en-US/offers?pickupDateFrom=2026-07-17&pickupDateTo=2027-07-17"
    },
    {
      "id": "252554_2742_3699",
      "offer_id": "252554",
      "route": "Homburg -> Marburg",
      "offer_type": 5,
      "vehicle": {
        "make": "Mystery",
        "model": "Auto",
        "description": null,
        "category": "Mystery Auto",
        "type": "Car",
        "class": null,
        "seats": 5,
        "doors": 5,
        "fuel_type": "Petrol",
        "gear_type": "Can be Manual/Automatic",
        "image": "https://storage.googleapis.com/movacar-prod-assets/eumystery.png"
      },
      "brand_image": "https://storage.googleapis.com/movacar-prod-assets/Europcar.png",
      "pickup": {
        "station_id": "1739",
        "city": "Homburg",
        "street": "BERLINER STR. 130",
        "postal_code": "66424",
        "latitude": 49.3406,
        "longitude": 7.3458,
        "code": "ZQWN01"
      },
      "dropoff": {
        "station_id": "1801",
        "city": "Marburg",
        "street": "AFFOELLERSTR. 82",
        "postal_code": "35039",
        "latitude": 50.8273,
        "longitude": 8.7699,
        "code": "ZOIC01"
      },
      "earliest_pickup": "2026-07-20T04:00:00Z",
      "latest_delivery": "2026-07-24T21:00:00Z",
      "latest_pickup": "2026-07-23T21:00:00+00:00",
      "valid_until": "2026-07-23T21:00:00Z",
      "included_period_hours": 24,
      "extra_period_hours": 24,
      "price": {
        "amount": 1.0,
        "currency": "EUR"
      },
      "free_km": 350,
      "cents_per_extra_km": 50,
      "route_distance_km": 257.1,
      "min_drivers_age": 18,
      "has_connections": false,
      "booking_link": "https://www.movacar.com/en-US/checkout/252554?origin=1739&destination=1801",
      "search_link": "https://www.movacar.com/en-US/offers?pickupDateFrom=2026-07-17&pickupDateTo=2027-07-17"
    },
    {
      "id": "252554_2742_4481",
      "offer_id": "252554",
      "route": "Homburg -> Offenbach am Main",
      "offer_type": 5,
      "vehicle": {
        "make": "Mystery",
        "model": "Auto",
        "description": null,
        "category": "Mystery Auto",
        "type": "Car",
        "class": null,
        "seats": 5,
        "doors": 5,
        "fuel_type": "Petrol",
        "gear_type": "Can be Manual/Automatic",
        "image": "https://storage.googleapis.com/movacar-prod-assets/eumystery.png"
      },
      "brand_image": "https://storage.googleapis.com/movacar-prod-assets/Europcar.png",
      "pickup": {
        "station_id": "1739",
        "city": "Homburg",
        "street": "BERLINER STR. 130",
        "postal_code": "66424",
        "latitude": 49.3406,
        "longitude": 7.3458,
        "code": "ZQWN01"
      },
      "dropoff": {
        "station_id": "1832",
        "city": "Offenbach am Main",
        "street": "SPRENDLINGER LANDSTR. 173 a",
        "postal_code": "63069",
        "latitude": 50.0852,
        "longitude": 8.7463,
        "code": "OFEC01"
      },
      "earliest_pickup": "2026-07-20T04:00:00Z",
      "latest_delivery": "2026-07-24T21:00:00Z",
      "latest_pickup": "2026-07-23T21:00:00+00:00",
      "valid_until": "2026-07-23T21:00:00Z",
      "included_period_hours": 24,
      "extra_period_hours": 24,
      "price": {
        "amount": 1.0,
        "currency": "EUR"
      },
      "free_km": 250,
      "cents_per_extra_km": 50,
      "route_distance_km": 171.9,
      "min_drivers_age": 18,
      "has_connections": false,
      "booking_link": "https://www.movacar.com/en-US/checkout/252554?origin=1739&destination=1832",
      "search_link": "https://www.movacar.com/en-US/offers?pickupDateFrom=2026-07-17&pickupDateTo=2027-07-17"
    },
    {
      "id": "252554_2742_5139",
      "offer_id": "252554",
      "route": "Homburg -> Rüsselsheim",
      "offer_type": 5,
      "vehicle": {
        "make": "Mystery",
        "model": "Auto",
        "description": null,
        "category": "Mystery Auto",
        "type": "Car",
        "class": null,
        "seats": 5,
        "doors": 5,
        "fuel_type": "Petrol",
        "gear_type": "Can be Manual/Automatic",
        "image": "https://storage.googleapis.com/movacar-prod-assets/eumystery.png"
      },
      "brand_image": "https://storage.googleapis.com/movacar-prod-assets/Europcar.png",
      "pickup": {
        "station_id": "1739",
        "city": "Homburg",
        "street": "BERLINER STR. 130",
        "postal_code": "66424",
        "latitude": 49.3406,
        "longitude": 7.3458,
        "code": "ZQWN01"
      },
      "dropoff": {
        "station_id": "1871",
        "city": "Rüsselsheim",
        "street": "STAHLSTR. 18",
        "postal_code": "65428",
        "latitude": 49.9762,
        "longitude": 8.432,
        "code": "ZPSC01"
      },
      "earliest_pickup": "2026-07-20T04:00:00Z",
      "latest_delivery": "2026-07-24T21:00:00Z",
      "latest_pickup": "2026-07-23T21:00:00+00:00",
      "valid_until": "2026-07-23T21:00:00Z",
      "included_period_hours": 24,
      "extra_period_hours": 24,
      "price": {
        "amount": 1.0,
        "currency": "EUR"
      },
      "free_km": 200,
      "cents_per_extra_km": 50,
      "route_distance_km": 129.6,
      "min_drivers_age": 18,
      "has_connections": false,
      "booking_link": "https://www.movacar.com/en-US/checkout/252554?origin=1739&destination=1871",
      "search_link": "https://www.movacar.com/en-US/offers?pickupDateFrom=2026-07-17&pickupDateTo=2027-07-17"
    },
    {
      "id": "252554_2742_6504",
      "offer_id": "252554",
      "route": "Homburg -> Wetzlar",
      "offer_type": 5,
      "vehicle": {
        "make": "Mystery",
        "model": "Auto",
        "description": null,
        "category": "Mystery Auto",
        "type": "Car",
        "class": null,
        "seats": 5,
        "doors": 5,
        "fuel_type": "Petrol",
        "gear_type": "Can be Manual/Automatic",
        "image": "https://storage.googleapis.com/movacar-prod-assets/eumystery.png"
      },
      "brand_image": "https://storage.googleapis.com/movacar-prod-assets/Europcar.png",
      "pickup": {
        "station_id": "1739",
        "city": "Homburg",
        "street": "BERLINER STR. 130",
        "postal_code": "66424",
        "latitude": 49.3406,
        "longitude": 7.3458,
        "code": "ZQWN01"
      },
      "dropoff": {
        "station_id": "1673",
        "city": "Wetzlar",
        "street": "ALTENBERGER STR. 55",
        "postal_code": "35576",
        "latitude": 50.5597,
        "longitude": 8.4848,
        "code": "GINW02"
      },
      "earliest_pickup": "2026-07-20T04:00:00Z",
      "latest_delivery": "2026-07-24T21:00:00Z",
      "latest_pickup": "2026-07-23T21:00:00+00:00",
      "valid_until": "2026-07-23T21:00:00Z",
      "included_period_hours": 24,
      "extra_period_hours": 24,
      "price": {
        "amount": 1.0,
        "currency": "EUR"
      },
      "free_km": 300,
      "cents_per_extra_km": 50,
      "route_distance_km": 227.6,
      "min_drivers_age": 18,
      "has_connections": false,
      "booking_link": "https://www.movacar.com/en-US/checkout/252554?origin=1739&destination=1673",
      "search_link": "https://www.movacar.com/en-US/offers?pickupDateFrom=2026-07-17&pickupDateTo=2027-07-17"
    },
    {
      "id": "252554_2742_6527",
      "offer_id": "252554",
      "route": "Homburg -> Wiesbaden",
      "offer_type": 5,
      "vehicle": {
        "make": "Mystery",
        "model": "Auto",
        "description": null,
        "category": "Mystery Auto",
        "type": "Car",
        "class": null,
        "seats": 5,
        "doors": 5,
        "fuel_type": "Petrol",
        "gear_type": "Can be Manual/Automatic",
        "image": "https://storage.googleapis.com/movacar-prod-assets/eumystery.png"
      },
      "brand_image": "https://storage.googleapis.com/movacar-prod-assets/Europcar.png",
      "pickup": {
        "station_id": "1739",
        "city": "Homburg",
        "street": "BERLINER STR. 130",
        "postal_code": "66424",
        "latitude": 49.3406,
        "longitude": 7.3458,
        "code": "ZQWN01"
      },
      "dropoff": {
        "station_id": "1915",
        "city": "Wiesbaden",
        "street": "MAINZER STR. 96",
        "postal_code": "65189",
        "latitude": 50.0679,
        "longitude": 8.2501,
        "code": "UWEC01"
      },
      "earliest_pickup": "2026-07-20T04:00:00Z",
      "latest_delivery": "2026-07-24T21:00:00Z",
      "latest_pickup": "2026-07-23T21:00:00+00:00",
      "valid_until": "2026-07-23T21:00:00Z",
      "included_period_hours": 24,
      "extra_period_hours": 24,
      "price": {
        "amount": 1.0,
        "currency": "EUR"
      },
      "free_km": 200,
      "cents_per_extra_km": 50,
      "route_distance_km": 135.6,
      "min_drivers_age": 18,
      "has_connections": false,
      "booking_link": "https://www.movacar.com/en-US/checkout/252554?origin=1739&destination=1915",
      "search_link": "https://www.movacar.com/en-US/offers?pickupDateFrom=2026-07-17&pickupDateTo=2027-07-17"
    },
    {
      "id": "252554_2742_19269",
      "offer_id": "252554",
      "route": "Homburg -> Kelsterbach",
      "offer_type": 5,
      "vehicle": {
        "make": "Mystery",
        "model": "Auto",
        "description": null,
        "category": "Mystery Auto",
        "type": "Car",
        "class": null,
        "seats": 5,
        "doors": 5,
        "fuel_type": "Petrol",
        "gear_type": "Can be Manual/Automatic",
        "image": "https://storage.googleapis.com/movacar-prod-assets/eumystery.png"
      },
      "brand_image": "https://storage.googleapis.com/movacar-prod-assets/Europcar.png",
      "pickup": {
        "station_id": "1739",
        "city": "Homburg",
        "street": "BERLINER STR. 130",
        "postal_code": "66424",
        "latitude": 49.3406,
        "longitude": 7.3458,
        "code": "ZQWN01"
      },
      "dropoff": {
        "station_id": "1585",
        "city": "Kelsterbach",
        "street": "AM ASPENHAAG 7",
        "postal_code": "65451",
        "latitude": 50.0512,
        "longitude": 8.5423,
        "code": "QLHC01"
      },
      "earliest_pickup": "2026-07-20T04:00:00Z",
      "latest_delivery": "2026-07-24T21:00:00Z",
      "latest_pickup": "2026-07-23T21:00:00+00:00",
      "valid_until": "2026-07-23T21:00:00Z",
      "included_period_hours": 24,
      "extra_period_hours": 24,
      "price": {
        "amount": 1.0,
        "currency": "EUR"
      },
      "free_km": 200,
      "cents_per_extra_km": 50,
      "route_distance_km": 144.5,
      "min_drivers_age": 18,
      "has_connections": false,
      "booking_link": "https://www.movacar.com/en-US/checkout/252554?origin=1739&destination=1585",
      "search_link": "https://www.movacar.com/en-US/offers?pickupDateFrom=2026-07-17&pickupDateTo=2027-07-17"
    },
    {
      "id": "252554_2742_22039",
      "offer_id": "252554",
      "route": "Homburg -> Diez",
      "offer_type": 5,
      "vehicle": {
        "make": "Mystery",
        "model": "Auto",
        "description": null,
        "category": "Mystery Auto",
        "type": "Car",
        "class": null,
        "seats": 5,
        "doors": 5,
        "fuel_type": "Petrol",
        "gear_type": "Can be Manual/Automatic",
        "image": "https://storage.googleapis.com/movacar-prod-assets/eumystery.png"
      },
      "brand_image": "https://storage.googleapis.com/movacar-prod-assets/Europcar.png",
      "pickup": {
        "station_id": "1739",
        "city": "Homburg",
        "street": "BERLINER STR. 130",
        "postal_code": "66424",
        "latitude": 49.3406,
        "longitude": 7.3458,
        "code": "ZQWN01"
      },
      "dropoff": {
        "station_id": "1447",
        "city": "Diez",
        "street": "LIMBURGER STR. 8C",
        "postal_code": "65582",
        "latitude": 50.3706,
        "longitude": 8.0269,
        "code": "DIZC02"
      },
      "earliest_pickup": "2026-07-20T04:00:00Z",
      "latest_delivery": "2026-07-24T21:00:00Z",
      "latest_pickup": "2026-07-23T21:00:00+00:00",
      "valid_until": "2026-07-23T21:00:00Z",
      "included_period_hours": 24,
      "extra_period_hours": 24,
      "price": {
        "amount": 1.0,
        "currency": "EUR"
      },
      "free_km": 250,
      "cents_per_extra_km": 50,
      "route_distance_km": 190.1,
      "min_drivers_age": 18,
      "has_connections": false,
      "booking_link": "https://www.movacar.com/en-US/checkout/252554?origin=1739&destination=1447",
      "search_link": "https://www.movacar.com/en-US/offers?pickupDateFrom=2026-07-17&pickupDateTo=2027-07-17"
    },
    {
      "id": "252539_2667_1557",
      "offer_id": "252539",
      "route": "Hof -> Erlangen",
      "offer_type": 5,
      "vehicle": {
        "make": "Transporter",
        "model": null,
        "description": null,
        "category": "TMHW - GR.3 IVECO",
        "type": "Car",
        "class": null,
        "seats": 3,
        "doors": 3,
        "fuel_type": "Diesel",
        "gear_type": "Manual",
        "image": "https://storage.googleapis.com/movacar-prod-assets/ecVMIW.png"
      },
      "brand_image": "https://storage.googleapis.com/movacar-prod-assets/Europcar.png",
      "pickup": {
        "station_id": "1735",
        "city": "Hof",
        "street": "OSSECKER STR. 179",
        "postal_code": "95030",
        "latitude": 50.3119,
        "longitude": 11.8814,
        "code": "HOQC02"
      },
      "dropoff": {
        "station_id": "1584",
        "city": "Erlangen",
        "street": "HILPERTSTR. 29",
        "postal_code": "91052",
        "latitude": 49.5864,
        "longitude": 11.0038,
        "code": "ERLC01"
      },
      "earliest_pickup": "2026-07-20T07:00:00Z",
      "latest_delivery": "2026-07-21T07:00:00Z",
      "latest_pickup": "2026-07-21T05:00:00+00:00",
      "valid_until": "2026-07-17T07:59:00Z",
      "included_period_hours": 24,
      "extra_period_hours": 24,
      "price": {
        "amount": 1.0,
        "currency": "EUR"
      },
      "free_km": 200,
      "cents_per_extra_km": 50,
      "route_distance_km": 139.4,
      "min_drivers_age": 21,
      "has_connections": false,
      "booking_link": "https://www.movacar.com/en-US/checkout/252539?origin=1735&destination=1584",
      "search_link": "https://www.movacar.com/en-US/offers?pickupDateFrom=2026-07-17&pickupDateTo=2027-07-17"
    },
    {
      "id": "252461_8082_202076",
      "offer_id": "252461",
      "route": "Palermo -> Olbia",
      "offer_type": 5,
      "vehicle": {
        "make": "Fiat",
        "model": "Ducato",
        "description": null,
        "category": "Active Poptop Select",
        "type": "Camper",
        "class": null,
        "seats": 4,
        "doors": 4,
        "fuel_type": "Diesel",
        "gear_type": "Manual",
        "image": "https://storage.googleapis.com/movacar-prod-assets/ZkJGSEFLKBtrW1B-_NOMADPOPTOP_HEROIMAGE.avif"
      },
      "brand_image": "https://storage.googleapis.com/movacar-prod-assets/IndieCampers.svg",
      "pickup": {
        "station_id": "6118",
        "city": "Palermo",
        "street": "Via Gazzara, 13",
        "postal_code": "90049",
        "latitude": 38.142823,
        "longitude": 13.089665,
        "code": "IC100"
      },
      "dropoff": {
        "station_id": "6163",
        "city": "Olbia",
        "street": "Strada Statale 125 Orientale Sarda",
        "postal_code": "07026",
        "latitude": 40.9030631,
        "longitude": 9.5328432,
        "code": "IC99"
      },
      "earliest_pickup": "2026-07-21T04:00:00Z",
      "latest_delivery": "2026-08-05T19:00:00Z",
      "latest_pickup": "2026-08-05T12:00:00+00:00",
      "valid_until": "2026-08-03T19:00:00Z",
      "included_period_hours": 48,
      "extra_period_hours": 48,
      "price": {
        "amount": 99.0,
        "currency": "EUR"
      },
      "free_km": 935,
      "cents_per_extra_km": 50,
      "route_distance_km": 689.9,
      "min_drivers_age": 18,
      "has_connections": true,
      "booking_link": "https://www.movacar.com/en-US/checkout/252461?origin=6118&destination=6163",
      "search_link": "https://www.movacar.com/en-US/offers?pickupDateFrom=2026-07-17&pickupDateTo=2027-07-17"
    },
    {
      "id": "252560_202076_7930",
      "offer_id": "252560",
      "route": "Olbia -> Cagliari",
      "offer_type": 5,
      "vehicle": {
        "make": "Fiat",
        "model": "Ducato",
        "description": null,
        "category": "Comfort Standard",
        "type": "Camper",
        "class": null,
        "seats": 4,
        "doors": 4,
        "fuel_type": "Diesel",
        "gear_type": "Manual",
        "image": "https://storage.googleapis.com/movacar-prod-assets/ZkIknEFLKBtrW0m0_005Atlas_@Sanojajesus_@Indie_Campers_-29.avif"
      },
      "brand_image": "https://storage.googleapis.com/movacar-prod-assets/IndieCampers.svg",
      "pickup": {
        "station_id": "6163",
        "city": "Olbia",
        "street": "Strada Statale 125 Orientale Sarda",
        "postal_code": "07026",
        "latitude": 40.9030631,
        "longitude": 9.5328432,
        "code": "IC99"
      },
      "dropoff": {
        "station_id": "6113",
        "city": "Cagliari",
        "street": "Strada dei Canadesi 2",
        "postal_code": "09032",
        "latitude": 39.278007,
        "longitude": 9.057308,
        "code": "IC94"
      },
      "earliest_pickup": "2026-07-24T04:00:00Z",
      "latest_delivery": "2026-08-01T19:00:00Z",
      "latest_pickup": "2026-08-01T16:00:00+00:00",
      "valid_until": "2026-07-29T19:00:00Z",
      "included_period_hours": 72,
      "extra_period_hours": 144,
      "price": {
        "amount": 1.0,
        "currency": "EUR"
      },
      "free_km": 462,
      "cents_per_extra_km": 50,
      "route_distance_km": 256.2,
      "min_drivers_age": 18,
      "has_connections": false,
      "booking_link": "https://www.movacar.com/en-US/checkout/252560?origin=6163&destination=6113",
      "search_link": "https://www.movacar.com/en-US/offers?pickupDateFrom=2026-07-17&pickupDateTo=2027-07-17"
    },
    {
      "id": "252563_202076_7930",
      "offer_id": "252563",
      "route": "Olbia -> Cagliari",
      "offer_type": 5,
      "vehicle": {
        "make": "Fiat",
        "model": "Ducato",
        "description": null,
        "category": "Comfort Standard",
        "type": "Camper",
        "class": null,
        "seats": 4,
        "doors": 4,
        "fuel_type": "Diesel",
        "gear_type": "Manual",
        "image": "https://storage.googleapis.com/movacar-prod-assets/ZkIknEFLKBtrW0m0_005Atlas_@Sanojajesus_@Indie_Campers_-29.avif"
      },
      "brand_image": "https://storage.googleapis.com/movacar-prod-assets/IndieCampers.svg",
      "pickup": {
        "station_id": "6163",
        "city": "Olbia",
        "street": "Strada Statale 125 Orientale Sarda",
        "postal_code": "07026",
        "latitude": 40.9030631,
        "longitude": 9.5328432,
        "code": "IC99"
      },
      "dropoff": {
        "station_id": "6113",
        "city": "Cagliari",
        "street": "Strada dei Canadesi 2",
        "postal_code": "09032",
        "latitude": 39.278007,
        "longitude": 9.057308,
        "code": "IC94"
      },
      "earliest_pickup": "2026-07-24T04:00:00Z",
      "latest_delivery": "2026-08-01T19:00:00Z",
      "latest_pickup": "2026-08-01T16:00:00+00:00",
      "valid_until": "2026-07-29T19:00:00Z",
      "included_period_hours": 72,
      "extra_period_hours": 144,
      "price": {
        "amount": 1.0,
        "currency": "EUR"
      },
      "free_km": 462,
      "cents_per_extra_km": 50,
      "route_distance_km": 256.2,
      "min_drivers_age": 18,
      "has_connections": false,
      "booking_link": "https://www.movacar.com/en-US/checkout/252563?origin=6163&destination=6113",
      "search_link": "https://www.movacar.com/en-US/offers?pickupDateFrom=2026-07-17&pickupDateTo=2027-07-17"
    },
    {
      "id": "252451_7502_202065",
      "offer_id": "252451",
      "route": "Lyon -> Saint-Mesmes",
      "offer_type": 5,
      "vehicle": {
        "make": "Fiat",
        "model": "Ducato",
        "description": null,
        "category": "Comfort Standard",
        "type": "Camper",
        "class": null,
        "seats": 4,
        "doors": 4,
        "fuel_type": "Diesel",
        "gear_type": "Manual",
        "image": "https://storage.googleapis.com/movacar-prod-assets/ZkIknEFLKBtrW0m0_005Atlas_@Sanojajesus_@Indie_Campers_-29.avif"
      },
      "brand_image": "https://storage.googleapis.com/movacar-prod-assets/IndieCampers.svg",
      "pickup": {
        "station_id": "6095",
        "city": "Lyon",
        "street": "256 Bcle de Satolas",
        "postal_code": "38540",
        "latitude": 45.667261,
        "longitude": 5.092593,
        "code": "IC74"
      },
      "dropoff": {
        "station_id": "6099",
        "city": "Saint-Mesmes",
        "street": "1 Chem. du Moulin de Tussac",
        "postal_code": "77410",
        "latitude": 48.9875914,
        "longitude": 2.691353,
        "code": "IC78"
      },
      "earliest_pickup": "2026-07-27T04:00:00Z",
      "latest_delivery": "2026-07-30T19:00:00Z",
      "latest_pickup": "2026-07-30T13:00:00+00:00",
      "valid_until": "2026-07-27T19:00:00Z",
      "included_period_hours": 72,
      "extra_period_hours": 72,
      "price": {
        "amount": 1.0,
        "currency": "EUR"
      },
      "free_km": 666,
      "cents_per_extra_km": 50,
      "route_distance_km": 526.4,
      "min_drivers_age": 18,
      "has_connections": false,
      "booking_link": "https://www.movacar.com/en-US/checkout/252451?origin=6095&destination=6099",
      "search_link": "https://www.movacar.com/en-US/offers?pickupDateFrom=2026-07-17&pickupDateTo=2027-07-17"
    },
    {
      "id": "252564_7502_202066",
      "offer_id": "252564",
      "route": "Lyon -> Grigny",
      "offer_type": 5,
      "vehicle": {
        "make": "Fiat",
        "model": "Ducato",
        "description": null,
        "category": "Comfort Standard",
        "type": "Camper",
        "class": null,
        "seats": 4,
        "doors": 4,
        "fuel_type": "Diesel",
        "gear_type": "Manual",
        "image": "https://storage.googleapis.com/movacar-prod-assets/ZkIknEFLKBtrW0m0_005Atlas_@Sanojajesus_@Indie_Campers_-29.avif"
      },
      "brand_image": "https://storage.googleapis.com/movacar-prod-assets/IndieCampers.svg",
      "pickup": {
        "station_id": "6095",
        "city": "Lyon",
        "street": "256 Bcle de Satolas",
        "postal_code": "38540",
        "latitude": 45.667261,
        "longitude": 5.092593,
        "code": "IC74"
      },
      "dropoff": {
        "station_id": "6100",
        "city": "Grigny",
        "street": "1 Rue des Batisseurs 3",
        "postal_code": "91350",
        "latitude": 48.74792,
        "longitude": 2.39253,
        "code": "IC79"
      },
      "earliest_pickup": "2026-07-28T04:00:00Z",
      "latest_delivery": "2026-08-02T19:00:00Z",
      "latest_pickup": "2026-08-02T14:00:00+00:00",
      "valid_until": "2026-07-30T19:00:00Z",
      "included_period_hours": 72,
      "extra_period_hours": 120,
      "price": {
        "amount": 1.0,
        "currency": "EUR"
      },
      "free_km": 658,
      "cents_per_extra_km": 50,
      "route_distance_km": 495.6,
      "min_drivers_age": 18,
      "has_connections": false,
      "booking_link": "https://www.movacar.com/en-US/checkout/252564?origin=6095&destination=6100",
      "search_link": "https://www.movacar.com/en-US/offers?pickupDateFrom=2026-07-17&pickupDateTo=2027-07-17"
    },
    {
      "id": "252571_10656_7923",
      "offer_id": "252571",
      "route": "Wiener Neudorf -> Bologna",
      "offer_type": 5,
      "vehicle": {
        "make": "Fiat",
        "model": "Ducato",
        "description": null,
        "category": "Active Standard Select",
        "type": "Camper",
        "class": null,
        "seats": 4,
        "doors": 4,
        "fuel_type": "Diesel",
        "gear_type": "Manual",
        "image": "https://storage.googleapis.com/movacar-prod-assets/aD_-qLh8WN-LVkic_ImageGrid-5-.avif"
      },
      "brand_image": "https://storage.googleapis.com/movacar-prod-assets/IndieCampers.svg",
      "pickup": {
        "station_id": "6089",
        "city": "Wiener Neudorf",
        "street": "Sofie-Lazarsfeld-Strasse 22",
        "postal_code": "1110",
        "latitude": 48.14047,
        "longitude": 16.44293,
        "code": "IC65"
      },
      "dropoff": {
        "station_id": "6112",
        "city": "Bologna",
        "street": "Via Corticella 50/A",
        "postal_code": "40013",
        "latitude": 44.554605,
        "longitude": 11.3202569,
        "code": "IC93"
      },
      "earliest_pickup": "2026-07-31T04:00:00Z",
      "latest_delivery": "2026-08-07T19:00:00Z",
      "latest_pickup": "2026-08-07T11:00:00+00:00",
      "valid_until": "2026-08-03T19:00:00Z",
      "included_period_hours": 96,
      "extra_period_hours": 168,
      "price": {
        "amount": 99.0,
        "currency": "EUR"
      },
      "free_km": 952,
      "cents_per_extra_km": 50,
      "route_distance_km": 766.8,
      "min_drivers_age": 18,
      "has_connections": false,
      "booking_link": "https://www.movacar.com/en-US/checkout/252571?origin=6089&destination=6112",
      "search_link": "https://www.movacar.com/en-US/offers?pickupDateFrom=2026-07-17&pickupDateTo=2027-07-17"
    },
    {
      "id": "252572_10656_7923",
      "offer_id": "252572",
      "route": "Wiener Neudorf -> Bologna",
      "offer_type": 5,
      "vehicle": {
        "make": "Fiat",
        "model": "Ducato",
        "description": null,
        "category": "Active Standard Select",
        "type": "Camper",
        "class": null,
        "seats": 4,
        "doors": 4,
        "fuel_type": "Diesel",
        "gear_type": "Manual",
        "image": "https://storage.googleapis.com/movacar-prod-assets/aD_-qLh8WN-LVkic_ImageGrid-5-.avif"
      },
      "brand_image": "https://storage.googleapis.com/movacar-prod-assets/IndieCampers.svg",
      "pickup": {
        "station_id": "6089",
        "city": "Wiener Neudorf",
        "street": "Sofie-Lazarsfeld-Strasse 22",
        "postal_code": "1110",
        "latitude": 48.14047,
        "longitude": 16.44293,
        "code": "IC65"
      },
      "dropoff": {
        "station_id": "6112",
        "city": "Bologna",
        "street": "Via Corticella 50/A",
        "postal_code": "40013",
        "latitude": 44.554605,
        "longitude": 11.3202569,
        "code": "IC93"
      },
      "earliest_pickup": "2026-07-31T04:00:00Z",
      "latest_delivery": "2026-08-07T19:00:00Z",
      "latest_pickup": "2026-08-07T11:00:00+00:00",
      "valid_until": "2026-08-03T19:00:00Z",
      "included_period_hours": 96,
      "extra_period_hours": 168,
      "price": {
        "amount": 99.0,
        "currency": "EUR"
      },
      "free_km": 952,
      "cents_per_extra_km": 50,
      "route_distance_km": 766.8,
      "min_drivers_age": 18,
      "has_connections": false,
      "booking_link": "https://www.movacar.com/en-US/checkout/252572?origin=6089&destination=6112",
      "search_link": "https://www.movacar.com/en-US/offers?pickupDateFrom=2026-07-17&pickupDateTo=2027-07-17"
    },
    {
      "id": "252573_10656_8053",
      "offer_id": "252573",
      "route": "Wiener Neudorf -> Milan",
      "offer_type": 5,
      "vehicle": {
        "make": "Ford",
        "model": "Transit/Jumper or similar",
        "description": null,
        "category": "Comfort Compact Select",
        "type": "Camper",
        "class": null,
        "seats": 4,
        "doors": 4,
        "fuel_type": "Diesel",
        "gear_type": "Automatic",
        "image": "https://storage.googleapis.com/movacar-prod-assets/aDgSKydWJ-7kSqXY_ImageGrid-6-.avif"
      },
      "brand_image": "https://storage.googleapis.com/movacar-prod-assets/IndieCampers.svg",
      "pickup": {
        "station_id": "6089",
        "city": "Wiener Neudorf",
        "street": "Sofie-Lazarsfeld-Strasse 22",
        "postal_code": "1110",
        "latitude": 48.14047,
        "longitude": 16.44293,
        "code": "IC65"
      },
      "dropoff": {
        "station_id": "6116",
        "city": "Milan",
        "street": "Via Giacomo Matteotti 6",
        "postal_code": "21010",
        "latitude": 45.6197196,
        "longitude": 8.7600985,
        "code": "IC97"
      },
      "earliest_pickup": "2026-07-31T04:00:00Z",
      "latest_delivery": "2026-08-07T19:00:00Z",
      "latest_pickup": "2026-08-07T10:00:00+00:00",
      "valid_until": "2026-08-03T19:00:00Z",
      "included_period_hours": 96,
      "extra_period_hours": 168,
      "price": {
        "amount": 99.0,
        "currency": "EUR"
      },
      "free_km": 1059,
      "cents_per_extra_km": 50,
      "route_distance_km": 872.5,
      "min_drivers_age": 18,
      "has_connections": false,
      "booking_link": "https://www.movacar.com/en-US/checkout/252573?origin=6089&destination=6116",
      "search_link": "https://www.movacar.com/en-US/offers?pickupDateFrom=2026-07-17&pickupDateTo=2027-07-17"
    },
    {
      "id": "252574_10656_8053",
      "offer_id": "252574",
      "route": "Wiener Neudorf -> Milan",
      "offer_type": 5,
      "vehicle": {
        "make": "Ford",
        "model": "Transit/Jumper or similar",
        "description": null,
        "category": "Comfort Compact Select",
        "type": "Camper",
        "class": null,
        "seats": 4,
        "doors": 4,
        "fuel_type": "Diesel",
        "gear_type": "Automatic",
        "image": "https://storage.googleapis.com/movacar-prod-assets/aDgSKydWJ-7kSqXY_ImageGrid-6-.avif"
      },
      "brand_image": "https://storage.googleapis.com/movacar-prod-assets/IndieCampers.svg",
      "pickup": {
        "station_id": "6089",
        "city": "Wiener Neudorf",
        "street": "Sofie-Lazarsfeld-Strasse 22",
        "postal_code": "1110",
        "latitude": 48.14047,
        "longitude": 16.44293,
        "code": "IC65"
      },
      "dropoff": {
        "station_id": "6116",
        "city": "Milan",
        "street": "Via Giacomo Matteotti 6",
        "postal_code": "21010",
        "latitude": 45.6197196,
        "longitude": 8.7600985,
        "code": "IC97"
      },
      "earliest_pickup": "2026-07-31T04:00:00Z",
      "latest_delivery": "2026-08-07T19:00:00Z",
      "latest_pickup": "2026-08-07T10:00:00+00:00",
      "valid_until": "2026-08-03T19:00:00Z",
      "included_period_hours": 96,
      "extra_period_hours": 168,
      "price": {
        "amount": 99.0,
        "currency": "EUR"
      },
      "free_km": 1059,
      "cents_per_extra_km": 50,
      "route_distance_km": 872.5,
      "min_drivers_age": 18,
      "has_connections": false,
      "booking_link": "https://www.movacar.com/en-US/checkout/252574?origin=6089&destination=6116",
      "search_link": "https://www.movacar.com/en-US/offers?pickupDateFrom=2026-07-17&pickupDateTo=2027-07-17"
    },
    {
      "id": "252578_10656_7917",
      "offer_id": "252578",
      "route": "Wiener Neudorf -> Bergamo",
      "offer_type": 5,
      "vehicle": {
        "make": "Fiat",
        "model": "Ducato",
        "description": null,
        "category": "Active Standard Select",
        "type": "Camper",
        "class": null,
        "seats": 4,
        "doors": 4,
        "fuel_type": "Diesel",
        "gear_type": "Manual",
        "image": "https://storage.googleapis.com/movacar-prod-assets/aD_-qLh8WN-LVkic_ImageGrid-5-.avif"
      },
      "brand_image": "https://storage.googleapis.com/movacar-prod-assets/IndieCampers.svg",
      "pickup": {
        "station_id": "6089",
        "city": "Wiener Neudorf",
        "street": "Sofie-Lazarsfeld-Strasse 22",
        "postal_code": "1110",
        "latitude": 48.14047,
        "longitude": 16.44293,
        "code": "IC65"
      },
      "dropoff": {
        "station_id": "6111",
        "city": "Bergamo",
        "street": "Via Aeroporto, 10/12",
        "postal_code": "24050",
        "latitude": 45.672881,
        "longitude": 9.686563,
        "code": "IC92"
      },
      "earliest_pickup": "2026-07-31T04:00:00Z",
      "latest_delivery": "2026-08-07T19:00:00Z",
      "latest_pickup": "2026-08-07T11:00:00+00:00",
      "valid_until": "2026-08-03T19:00:00Z",
      "included_period_hours": 96,
      "extra_period_hours": 168,
      "price": {
        "amount": 99.0,
        "currency": "EUR"
      },
      "free_km": 1020,
      "cents_per_extra_km": 50,
      "route_distance_km": 793.2,
      "min_drivers_age": 18,
      "has_connections": false,
      "booking_link": "https://www.movacar.com/en-US/checkout/252578?origin=6089&destination=6111",
      "search_link": "https://www.movacar.com/en-US/offers?pickupDateFrom=2026-07-17&pickupDateTo=2027-07-17"
    },
    {
      "id": "252579_10656_7917",
      "offer_id": "252579",
      "route": "Wiener Neudorf -> Bergamo",
      "offer_type": 5,
      "vehicle": {
        "make": "Fiat",
        "model": "Ducato",
        "description": null,
        "category": "Active Standard Select",
        "type": "Camper",
        "class": null,
        "seats": 4,
        "doors": 4,
        "fuel_type": "Diesel",
        "gear_type": "Manual",
        "image": "https://storage.googleapis.com/movacar-prod-assets/aD_-qLh8WN-LVkic_ImageGrid-5-.avif"
      },
      "brand_image": "https://storage.googleapis.com/movacar-prod-assets/IndieCampers.svg",
      "pickup": {
        "station_id": "6089",
        "city": "Wiener Neudorf",
        "street": "Sofie-Lazarsfeld-Strasse 22",
        "postal_code": "1110",
        "latitude": 48.14047,
        "longitude": 16.44293,
        "code": "IC65"
      },
      "dropoff": {
        "station_id": "6111",
        "city": "Bergamo",
        "street": "Via Aeroporto, 10/12",
        "postal_code": "24050",
        "latitude": 45.672881,
        "longitude": 9.686563,
        "code": "IC92"
      },
      "earliest_pickup": "2026-07-31T04:00:00Z",
      "latest_delivery": "2026-08-07T19:00:00Z",
      "latest_pickup": "2026-08-07T11:00:00+00:00",
      "valid_until": "2026-08-03T19:00:00Z",
      "included_period_hours": 96,
      "extra_period_hours": 168,
      "price": {
        "amount": 99.0,
        "currency": "EUR"
      },
      "free_km": 1020,
      "cents_per_extra_km": 50,
      "route_distance_km": 793.2,
      "min_drivers_age": 18,
      "has_connections": false,
      "booking_link": "https://www.movacar.com/en-US/checkout/252579?origin=6089&destination=6111",
      "search_link": "https://www.movacar.com/en-US/offers?pickupDateFrom=2026-07-17&pickupDateTo=2027-07-17"
    },
    {
      "id": "252570_10656_8053",
      "offer_id": "252570",
      "route": "Wiener Neudorf -> Milan",
      "offer_type": 5,
      "vehicle": {
        "make": "Fiat",
        "model": "Ducato",
        "description": null,
        "category": "Active Poptop",
        "type": "Camper",
        "class": null,
        "seats": 4,
        "doors": 4,
        "fuel_type": "Diesel",
        "gear_type": "Manual",
        "image": "https://storage.googleapis.com/movacar-prod-assets/ZkJGSEFLKBtrW1B-_NOMADPOPTOP_HEROIMAGE.avif"
      },
      "brand_image": "https://storage.googleapis.com/movacar-prod-assets/IndieCampers.svg",
      "pickup": {
        "station_id": "6089",
        "city": "Wiener Neudorf",
        "street": "Sofie-Lazarsfeld-Strasse 22",
        "postal_code": "1110",
        "latitude": 48.14047,
        "longitude": 16.44293,
        "code": "IC65"
      },
      "dropoff": {
        "station_id": "6116",
        "city": "Milan",
        "street": "Via Giacomo Matteotti 6",
        "postal_code": "21010",
        "latitude": 45.6197196,
        "longitude": 8.7600985,
        "code": "IC97"
      },
      "earliest_pickup": "2026-08-02T04:00:00Z",
      "latest_delivery": "2026-08-09T19:00:00Z",
      "latest_pickup": "2026-08-09T10:00:00+00:00",
      "valid_until": "2026-08-05T19:00:00Z",
      "included_period_hours": 96,
      "extra_period_hours": 168,
      "price": {
        "amount": 99.0,
        "currency": "EUR"
      },
      "free_km": 1059,
      "cents_per_extra_km": 50,
      "route_distance_km": 872.5,
      "min_drivers_age": 18,
      "has_connections": false,
      "booking_link": "https://www.movacar.com/en-US/checkout/252570?origin=6089&destination=6116",
      "search_link": "https://www.movacar.com/en-US/offers?pickupDateFrom=2026-07-17&pickupDateTo=2027-07-17"
    },
    {
      "id": "252464_7537_7604",
      "offer_id": "252464",
      "route": "Nice -> Toulouse",
      "offer_type": 5,
      "vehicle": {
        "make": "Fiat",
        "model": "Ducato",
        "description": null,
        "category": "Comfort Standard",
        "type": "Camper",
        "class": null,
        "seats": 4,
        "doors": 4,
        "fuel_type": "Diesel",
        "gear_type": "Manual",
        "image": "https://storage.googleapis.com/movacar-prod-assets/ZkIknEFLKBtrW0m0_005Atlas_@Sanojajesus_@Indie_Campers_-29.avif"
      },
      "brand_image": "https://storage.googleapis.com/movacar-prod-assets/IndieCampers.svg",
      "pickup": {
        "station_id": "6098",
        "city": "Nice",
        "street": "215 Chemin de la Romaine",
        "postal_code": "06600",
        "latitude": 43.6159547,
        "longitude": 7.1111765,
        "code": "IC77"
      },
      "dropoff": {
        "station_id": "6101",
        "city": "Toulouse",
        "street": "9 bis chemin de la Gravire, lot 4",
        "postal_code": "31150",
        "latitude": 43.714399,
        "longitude": 1.3889351,
        "code": "IC80"
      },
      "earliest_pickup": "2026-08-04T04:00:00Z",
      "latest_delivery": "2026-08-06T19:00:00Z",
      "latest_pickup": "2026-08-06T13:00:00+00:00",
      "valid_until": "2026-08-04T19:00:00Z",
      "included_period_hours": 48,
      "extra_period_hours": 48,
      "price": {
        "amount": 1.0,
        "currency": "EUR"
      },
      "free_km": 775,
      "cents_per_extra_km": 50,
      "route_distance_km": 561.6,
      "min_drivers_age": 18,
      "has_connections": false,
      "booking_link": "https://www.movacar.com/en-US/checkout/252464?origin=6098&destination=6101",
      "search_link": "https://www.movacar.com/en-US/offers?pickupDateFrom=2026-07-17&pickupDateTo=2027-07-17"
    },
    {
      "id": "252575_10656_7923",
      "offer_id": "252575",
      "route": "Wiener Neudorf -> Bologna",
      "offer_type": 5,
      "vehicle": {
        "make": "Fiat",
        "model": "S 75SL / T 7400 SB or similar",
        "description": null,
        "category": "Comfort Long Select",
        "type": "Camper",
        "class": null,
        "seats": 4,
        "doors": 4,
        "fuel_type": "Diesel",
        "gear_type": "Automatic",
        "image": "https://storage.googleapis.com/movacar-prod-assets/aaca0lxvIZEnjSPD_FAMILY@5x.avif"
      },
      "brand_image": "https://storage.googleapis.com/movacar-prod-assets/IndieCampers.svg",
      "pickup": {
        "station_id": "6089",
        "city": "Wiener Neudorf",
        "street": "Sofie-Lazarsfeld-Strasse 22",
        "postal_code": "1110",
        "latitude": 48.14047,
        "longitude": 16.44293,
        "code": "IC65"
      },
      "dropoff": {
        "station_id": "6112",
        "city": "Bologna",
        "street": "Via Corticella 50/A",
        "postal_code": "40013",
        "latitude": 44.554605,
        "longitude": 11.3202569,
        "code": "IC93"
      },
      "earliest_pickup": "2026-08-04T04:00:00Z",
      "latest_delivery": "2026-08-11T19:00:00Z",
      "latest_pickup": "2026-08-11T11:00:00+00:00",
      "valid_until": "2026-08-07T19:00:00Z",
      "included_period_hours": 96,
      "extra_period_hours": 168,
      "price": {
        "amount": 99.0,
        "currency": "EUR"
      },
      "free_km": 952,
      "cents_per_extra_km": 50,
      "route_distance_km": 766.8,
      "min_drivers_age": 18,
      "has_connections": false,
      "booking_link": "https://www.movacar.com/en-US/checkout/252575?origin=6089&destination=6112",
      "search_link": "https://www.movacar.com/en-US/offers?pickupDateFrom=2026-07-17&pickupDateTo=2027-07-17"
    },
    {
      "id": "252580_7502_7537",
      "offer_id": "252580",
      "route": "Lyon -> Nice",
      "offer_type": 5,
      "vehicle": {
        "make": "Fiat",
        "model": "Ducato",
        "description": null,
        "category": "Comfort Standard",
        "type": "Camper",
        "class": null,
        "seats": 4,
        "doors": 4,
        "fuel_type": "Diesel",
        "gear_type": "Manual",
        "image": "https://storage.googleapis.com/movacar-prod-assets/ZkIknEFLKBtrW0m0_005Atlas_@Sanojajesus_@Indie_Campers_-29.avif"
      },
      "brand_image": "https://storage.googleapis.com/movacar-prod-assets/IndieCampers.svg",
      "pickup": {
        "station_id": "6095",
        "city": "Lyon",
        "street": "256 Bcle de Satolas",
        "postal_code": "38540",
        "latitude": 45.667261,
        "longitude": 5.092593,
        "code": "IC74"
      },
      "dropoff": {
        "station_id": "6098",
        "city": "Nice",
        "street": "215 Chemin de la Romaine",
        "postal_code": "06600",
        "latitude": 43.6159547,
        "longitude": 7.1111765,
        "code": "IC77"
      },
      "earliest_pickup": "2026-08-18T04:00:00Z",
      "latest_delivery": "2026-09-23T19:00:00Z",
      "latest_pickup": "2026-09-23T14:00:00+00:00",
      "valid_until": "2026-09-20T19:00:00Z",
      "included_period_hours": 72,
      "extra_period_hours": 144,
      "price": {
        "amount": 1.0,
        "currency": "EUR"
      },
      "free_km": 678,
      "cents_per_extra_km": 50,
      "route_distance_km": 469.2,
      "min_drivers_age": 18,
      "has_connections": false,
      "booking_link": "https://www.movacar.com/en-US/checkout/252580?origin=6095&destination=6098",
      "search_link": "https://www.movacar.com/en-US/offers?pickupDateFrom=2026-07-17&pickupDateTo=2027-07-17"
    }
  ]
}